[
	{
		"id": 1,
		"title": "Lesson 1 · Spell Your Name in ASL",
		"kind": "spell-name",
		"summary": "Use your webcam to practice the ASL alphabet letter-by-letter with your own name.",
		"questionCount": 0,
		"points": 150,
		"imageUrl": "https://upload.wikimedia.org/wikipedia/commons/thumb/4/40/Sign_language_alphabet.svg/512px-Sign_language_alphabet.svg.png"
	},
	{
		"id": 2,
		"title": "Lesson 2 - Learn the alphabet!",
		"questionCount": 10,
		"points": 180,
		"progress": 0,
		"questions": []
	},
	{
		"id": 3,
		"title": "Lesson 3 - Learn common words!",
		"questionCount": 7,
		"points": 150,
		"progress": 0,
		"questions": []
	}
]
